biom/_subsample.cpython-37m-x86_64-linux-gnu.so
biom/table.py
biom/_transform.pyx
biom/_filter.cpython-37m-x86_64-linux-gnu.so
biom/_transform.cpython-37m-x86_64-linux-gnu.so
biom/_subsample.pyx
biom/__init__.py
biom/parse.py
biom/err.py
biom/util.py
biom/_filter.pyx
biom/exception.py
biom/assets/exercise_api.py
biom/assets/exercise_cli.sh
biom/cli/installation_informer.py
biom/cli/uc_processor.py
biom/cli/metadata_adder.py
biom/cli/table_converter.py
biom/cli/table_subsetter.py
biom/cli/table_summarizer.py
biom/cli/table_normalizer.py
biom/cli/table_head.py
biom/cli/__init__.py
biom/cli/table_validator.py
biom/cli/metadata_exporter.py
biom/cli/util.py
biom/cli/table_ids.py
biom/tests/test_util.py
biom/tests/long_lines.py
biom/tests/test_table.py
biom/tests/__init__.py
biom/tests/test_err.py
biom/tests/test_parse.py
biom/tests/test_cli/test_summarize_table.py
biom/tests/test_cli/test_add_metadata.py
biom/tests/test_cli/test_uc_processor.py
biom/tests/test_cli/test_validate_table.py
biom/tests/test_cli/__init__.py
biom/tests/test_cli/test_table_converter.py
biom/tests/test_cli/test_table_normalizer.py
biom/tests/test_cli/test_show_install_info.py
biom/tests/test_cli/test_subset_table.py
biom/tests/test_cli/test_data/json_sample_collapsed.biom
biom/tests/test_cli/test_data/test.json
biom/tests/test_cli/test_data/test.biom
biom/tests/test_cli/test_data/json_obs_collapsed.biom
biom/tests/test_data/bad_table.txt.gz
biom/tests/test_data/test.json
biom/tests/test_data/test.json.gz
biom/tests/test_data/bad_table.txt
biom/tests/test_data/__init__.py
biom/tests/test_data/no-contents.biom
biom/tests/test_data/test.biom
biom/tests/test_data/test_grp_metadata.biom
biom/tests/test_data/empty.biom
biom/tests/bench_tables/1000x10x0.100_bench_hdf5.biom.gz
biom/tests/bench_tables/10x1000x0.100_bench.biom.gz
biom/tests/bench_tables/10x100x0.010_bench.biom.gz
biom/tests/bench_tables/100x10000x0.100_bench.biom.gz
biom_format-2.1.15.dist-info/METADATA
biom_format-2.1.15.dist-info/entry_points.txt
biom_format-2.1.15.dist-info/top_level.txt
biom_format-2.1.15.dist-info/RECORD
biom_format-2.1.15.dist-info/COPYING.txt
biom_format-2.1.15.dist-info/WHEEL
