Metadata-Version: 2.1
Name: biom-format
Version: 2.1.15
Summary: Biological Observation Matrix (BIOM) format
Home-page: http://www.biom-format.org
Author: Daniel McDonald
Author-email: mcdonadt@colorado.edu
Maintainer: Daniel McDonald
Maintainer-email: mcdonadt@colorado.edu
License: BSD
Classifier: Development Status :: 4 - Beta
Classifier: License :: OSI Approved :: BSD License
Classifier: Topic :: Scientific/Engineering :: Bio-Informatics
Classifier: Topic :: Software Development :: Libraries :: Application Frameworks
Classifier: Topic :: Software Development :: Libraries :: Python Modules
Classifier: Programming Language :: Python
Classifier: Programming Language :: Python :: 3.6
Classifier: Programming Language :: Python :: 3.7
Classifier: Programming Language :: Python :: 3.8
Classifier: Programming Language :: Python :: 3.9
Classifier: Programming Language :: Python :: 3.10
Classifier: Programming Language :: Python :: Implementation :: CPython
Classifier: Operating System :: OS Independent
Classifier: Operating System :: POSIX :: Linux
Classifier: Operating System :: MacOS :: MacOS X
Requires-Python: >=3.6
Provides-Extra: hdf5
Provides-Extra: anndata
License-File: COPYING.txt
